aioanixart/__init__.py
aioanixart/api.py
aioanixart/collections.py
aioanixart/endpoints.py
aioanixart/exceptions.py
aioanixart/profile.py
aioanixart/release.py
aioanixart/request_handler.py
aioanixart/types.py
aioanixart-24.2.23.dist-info/LICENSE
aioanixart-24.2.23.dist-info/METADATA
aioanixart-24.2.23.dist-info/WHEEL
aioanixart-24.2.23.dist-info/top_level.txt
aioanixart-24.2.23.dist-info/RECORD
