Metadata-Version: 2.1
Name: aioanixart
Version: 24.2.23
Summary: Asynchronous wrapper for Anixart API
Home-page: https://github.com/ca4tuk/aioanixart
Author: ca4tuk
Author-email: ca4tuk@gmail.com
License: GPL-3.0
Project-URL: Source, https://github.com/ca4tuk/manga-in-ua
Classifier: Intended Audience :: Developers
Classifier: Natural Language :: Russian
Classifier: Programming Language :: Python :: 3 :: Only
Classifier: Programming Language :: Python :: 3
Classifier: Programming Language :: Python :: 3.8
Classifier: License :: Other/Proprietary License
Classifier: Operating System :: OS Independent
Requires-Python: >=3.8
License-File: LICENSE
Requires-Dist: aiohttp
